rolete/__init__.py
rolete/class_rolete.py
rolete/run_rolete.py
rolete/version.py
window_blinds_rpi/__init__.py
window_blinds_rpi/blinds_circuit.py
window_blinds_rpi/mcp_expander.py
window_blinds_rpi/runnable_blinds.py
window_blinds_rpi/version.py
rolete-1.2.3.dist-info/LICENSE
rolete-1.2.3.dist-info/METADATA
rolete-1.2.3.dist-info/WHEEL
rolete-1.2.3.dist-info/top_level.txt
rolete-1.2.3.dist-info/RECORD
