Metadata-Version: 2.1
Name: rolete
Version: 1.2.3
Summary: Show how to structure a Python project.
Home-page: https://github.com/bast/rolete
Author: Bruce Wayne
Author-email: bruce.wayne@example.com
License: MPL-2.0
Platform: UNKNOWN
Classifier: Development Status :: 5 - Production/Stable
Classifier: Intended Audience :: Science/Research
Classifier: Programming Language :: Python :: 2.7
Classifier: Programming Language :: Python :: 3.6
